seaplane_framework/api/__init__.py
seaplane_framework/api/api_client.py
seaplane_framework/api/configuration.py
seaplane_framework/api/exceptions.py
seaplane_framework/api/rest.py
seaplane_framework/api/schemas.py
seaplane_framework/api/apis/__init__.py
seaplane_framework/api/apis/path_to_api.py
seaplane_framework/api/apis/tag_to_api.py
seaplane_framework/api/apis/paths/__init__.py
seaplane_framework/api/apis/paths/endpoints_endpoint_request.py
seaplane_framework/api/apis/paths/endpoints_endpoint_response_message_id.py
seaplane_framework/api/apis/paths/endpoints_endpoint_response_message_id_archive.py
seaplane_framework/api/apis/paths/endpoints_endpoint_response_request_id.py
seaplane_framework/api/apis/paths/flow.py
seaplane_framework/api/apis/paths/flow_flow_name.py
seaplane_framework/api/apis/paths/flow_flow_name_events.py
seaplane_framework/api/apis/paths/flow_flow_name_secrets.py
seaplane_framework/api/apis/paths/flow_flow_name_secrets_secret_name.py
seaplane_framework/api/apis/paths/flow_flow_name_status.py
seaplane_framework/api/apis/paths/kv.py
seaplane_framework/api/apis/paths/kv_kv_store.py
seaplane_framework/api/apis/paths/kv_kv_store_key.py
seaplane_framework/api/apis/paths/kv_kv_store_key_key.py
seaplane_framework/api/apis/paths/object.py
seaplane_framework/api/apis/paths/object_bucket_name.py
seaplane_framework/api/apis/paths/object_bucket_name_list.py
seaplane_framework/api/apis/paths/object_bucket_name_store.py
seaplane_framework/api/apis/paths/stream.py
seaplane_framework/api/apis/paths/stream_stream_name.py
seaplane_framework/api/apis/paths/webhook_provider_division.py
seaplane_framework/api/apis/tags/__init__.py
seaplane_framework/api/apis/tags/endpoint_api.py
seaplane_framework/api/apis/tags/flow_api.py
seaplane_framework/api/apis/tags/key_value_api.py
seaplane_framework/api/apis/tags/object_api.py
seaplane_framework/api/apis/tags/stream_api.py
seaplane_framework/api/apis/tags/webhook_api.py
seaplane_framework/api/model/__init__.py
seaplane_framework.api-0.0.13.dist-info/LICENSE
seaplane_framework.api-0.0.13.dist-info/METADATA
seaplane_framework.api-0.0.13.dist-info/WHEEL
seaplane_framework.api-0.0.13.dist-info/top_level.txt
seaplane_framework.api-0.0.13.dist-info/RECORD
