Metadata-Version: 2.1
Name: seaplane-framework.api
Version: 0.0.13
Summary: Carrier API
Home-page: 
Author: Seaplane IO, Inc.
Author-email: support@seaplane.io
License: Apache 2.0
Keywords: OpenAPI,OpenAPI-Generator,Carrier API
Requires-Python: >=3.7
License-File: LICENSE
Requires-Dist: certifi >=14.5.14
Requires-Dist: frozendict ~=2.3.4
Requires-Dist: python-dateutil >=2.7
Requires-Dist: setuptools >=21.0.0
Requires-Dist: typing-extensions ~=4.6.0
Requires-Dist: urllib3 ~=1.26.7
